cqcalendar/__init__.py
cqcalendar/cqcalendar.py
cqcalendar-1.5.0.dist-info/licenses/LICENSE
cqcalendar-1.5.0.dist-info/METADATA
cqcalendar-1.5.0.dist-info/WHEEL
cqcalendar-1.5.0.dist-info/top_level.txt
cqcalendar-1.5.0.dist-info/RECORD
