Metadata-Version: 2.4
Name: cqcalendar
Version: 1.5.0
Summary: CQCalendar is a lightweight, tick-based time and calendar system for Python games and simulations.
Author: Brianna Ladson
License: MIT
Keywords: rpg,simulation,game-dev,time-system,calendar,tick-based,worldbuilding,sandbox
Classifier: Development Status :: 4 - Beta
Classifier: Intended Audience :: Developers
Classifier: Programming Language :: Python :: 3
Classifier: License :: OSI Approved :: MIT License
Classifier: Operating System :: OS Independent
Classifier: Topic :: Games/Entertainment
Classifier: Topic :: Software Development :: Libraries :: Python Modules
Requires-Python: >=3.7
License-File: LICENSE
Dynamic: license-file
